README.md
setup.py
easyELM/ELM.py
easyELM/__init__.py
easyELM.egg-info/PKG-INFO
easyELM.egg-info/SOURCES.txt
easyELM.egg-info/dependency_links.txt
easyELM.egg-info/requires.txt
easyELM.egg-info/top_level.txt