Metadata-Version: 1.0
Name: easyELM
Version: 1.0
Summary: Extreme Learning Machine implentation
Home-page: https://github.com/alvarogrgz/easyELM
Author: Álvaro García González
Author-email: alvarogrgz@gmail.com
License: MIT
Platform: UNKNOWN
